ikieksfeg/__init__.py
ikieksfeg/hello.py
ikieksfeg-0.0.2.dist-info/METADATA
ikieksfeg-0.0.2.dist-info/WHEEL
ikieksfeg-0.0.2.dist-info/top_level.txt
ikieksfeg-0.0.2.dist-info/RECORD
