Metadata-Version: 2.1
Name: ikieksfeg
Version: 0.0.2
Summary: kekw
Author: Jonas
Author-email: kekw@kekw.kekw
Keywords: python
Classifier: Operating System :: Microsoft :: Windows
